helpdsf/__init__.py
helpdsf/helpdsfx.py
HelpDSFx-0.2.dist-info/LICENSE
HelpDSFx-0.2.dist-info/METADATA
HelpDSFx-0.2.dist-info/WHEEL
HelpDSFx-0.2.dist-info/top_level.txt
HelpDSFx-0.2.dist-info/RECORD
