Metadata-Version: 2.1
Name: HelpDSFx
Version: 0.2
Summary: Библиотека для взаимодействия с DeepSeek через aitunnel.ru
Home-page: https://github.com/ваш_репозиторий/HelpDSFx
Author: Ваше Имя
Author-email: ваш.email@example.com
Classifier: Programming Language :: Python :: 3
Classifier: License :: OSI Approved :: MIT License
Classifier: Operating System :: OS Independent
Requires-Python: >=3.6
License-File: LICENSE
Requires-Dist: openai
